heq.py
heq-0.0.3.dist-info/METADATA
heq-0.0.3.dist-info/WHEEL
heq-0.0.3.dist-info/entry_points.txt
heq-0.0.3.dist-info/top_level.txt
heq-0.0.3.dist-info/RECORD
