Metadata-Version: 2.1
Name: heq
Version: 0.0.3
Summary: Yet another 'jq for HTML'
Home-page: https://github.com/atodekangae/heq
Author: atodekangae
Author-email: atodekangae@gmail.com
Classifier: Programming Language :: Python :: 3
Classifier: Programming Language :: Python :: 3.8
Classifier: Programming Language :: Python :: 3.9
Classifier: Programming Language :: Python :: 3.10
Classifier: Programming Language :: Python :: 3.11
Classifier: Programming Language :: Python :: 3.12
Classifier: Operating System :: OS Independent
Classifier: Topic :: Text Processing :: Markup :: HTML
Classifier: Environment :: Console
Requires-Python: >=3.8
Requires-Dist: lxml[cssselect] >=4
Requires-Dist: parsimonious >=0.10.0
Provides-Extra: dev
Requires-Dist: pytest <7.0,>=6.0 ; extra == 'dev'
